sensecam_control/__init__.py
sensecam_control/onvif_config.py
sensecam_control/onvif_control.py
sensecam_control/vapix_config.py
sensecam_control/vapix_control.py
sensecam_control-0.1.0.dist-info/LICENSE.txt
sensecam_control-0.1.0.dist-info/METADATA
sensecam_control-0.1.0.dist-info/WHEEL
sensecam_control-0.1.0.dist-info/top_level.txt
sensecam_control-0.1.0.dist-info/RECORD
