Metadata-Version: 2.1
Name: sensecam-control
Version: 0.1.0
Summary: Implementation of python functions for control and configuration of Axis cameras using Vapix/Onvif.
Home-page: https://github.com/smartsenselab/sensecam-control
Author: Igor Dias
Author-email: igorhenriquedias94@gmail.com
License: MIT
Keywords: ONVIF,vapix,camera
Platform: UNKNOWN
Classifier: Programming Language :: Python :: 3
Classifier: License :: OSI Approved :: MIT License
Classifier: Operating System :: OS Independent
Requires-Python: >=3.6
Requires-Dist: urllib3 (>=1.25.7)
Requires-Dist: requests (>=2.22.0)
Requires-Dist: beautifulsoup4 (>=4.8.1)
Requires-Dist: onvif-zeep (>=0.2.12)
